semgrep_agent/__init__.py
semgrep_agent/__main__.py
semgrep_agent/constants.py
semgrep_agent/exc.py
semgrep_agent/findings.py
semgrep_agent/formatter.py
semgrep_agent/ignores.py
semgrep_agent/main.py
semgrep_agent/meta.py
semgrep_agent/semgrep.py
semgrep_agent/semgrep_app.py
semgrep_agent/targets.py
semgrep_agent/templates/.semgrepignore
semgrep_agent/utils.py
semgrep_agent/yaml.py
semgrep_agent-0.1.0b2.dist-info/entry_points.txt
semgrep_agent-0.1.0b2.dist-info/LICENSE
semgrep_agent-0.1.0b2.dist-info/WHEEL
semgrep_agent-0.1.0b2.dist-info/METADATA
semgrep_agent-0.1.0b2.dist-info/RECORD
