Metadata-Version: 2.1
Name: semgrep-agent
Version: 0.1.0b2
Summary: 
License: Proprietary
Author: Return To Corporation
Author-email: support@r2c.dev
Requires-Python: >=3.7,<4.0
Classifier: License :: Other/Proprietary License
Classifier: Programming Language :: Python :: 3
Classifier: Programming Language :: Python :: 3.10
Classifier: Programming Language :: Python :: 3.7
Classifier: Programming Language :: Python :: 3.8
Classifier: Programming Language :: Python :: 3.9
Requires-Dist: GitPython (>=3.1.11,<4.0.0)
Requires-Dist: PyYAML (>=5.4.1,<6.0.0)
Requires-Dist: attrs (>=20.3,<22.0)
Requires-Dist: boltons (>=20.2.1,<22.0.0)
Requires-Dist: click (>=7.1.2,<9.0.0)
Requires-Dist: glom (>=20.8.0,<21.0.0)
Requires-Dist: pymmh3 (>=0.0.5,<0.0.6)
Requires-Dist: requests (>=2.24.0,<3.0.0)
Requires-Dist: sh (>=1.13.1,<2.0.0)
